{
  "type": "base",
  "metadata": [],
  "title": "A-Mass Flooring & Tile | Massachusetts Flooring and Tile Experts",
  "lang": "en",
  "description": "Top-rated Massachusetts flooring and tile company offering expert residential and commercial services in tile, hardwood flooring, dustless sanding, luxury vinyl plank and tile (LVP/LVT), carpet, VCT, rubber, and sheet flooring. We also specialize in high-quality kitchen and bathroom renovations.",
  "image": "/assets/logo/logo-black.svg",
  "scripts": [
    {
      "async": true,
      "src": "https://www.googletagmanager.com/gtag/js?id=G-XCXJ3YGVFC"
    },
    "window.dataLayer = window.dataLayer || []; function gtag(){dataLayer.push(arguments);} gtag('js', new Date()); gtag('config', 'G-XCXJ3YGVFC');"
  ],
  "stylesheets": [
    "@font-face { font-family: 'Fjalla One'; src: url('/assets/fonts/Fjalla_One/FjallaOne-Regular.ttf') format('truetype'); font-weight: normal; }",
    "*, ::after, ::before { box-sizing: border-box; }",
    "html { font-family: system-ui, 'Segoe UI', Roboto, Helvetica, Arial, sans-serif, 'Apple Color Emoji', 'Segoe UI Emoji'; line-height: 1.15; -webkit-text-size-adjust: 100%; tab-size: 4; height: 100%; }",
    "body { margin: 0; width: 100%; height: 100%; font-family: Open Sans, sans-serif; color: #fff; letter-spacing: 0.06rem; }",
    "[hidden] { display: none; }",
    "h1, h2, h3, h4, h5, h6 { font-family: 'Fjalla One', sans-serif; letter-spacing: 2px; font-weight: 500; margin-top: 0; line-height: 1.2; }",
    "p { margin-top: 0; line-height: 1.2; }",
    "span { display: inline-block; }",
    "b, strong { font-weight: bolder; }",
    "small { font-size: 60%; }",
    "button, input, optgroup, select, textarea { font-family: inherit; font-size: 100%; line-height: 1.15; margin: 0; background: none; }",
    "[type='button'], [type='reset'], [type='submit'], button { -webkit-appearance: button; cursor: pointer; }",
    ".content { height: 100%; overflow-y: scroll; scroll-snap-type: y mandatory; scroll-behavior: smooth;}",
    ".wrapper { width: 100%; max-width: 1200px; padding: 0 25px; margin: 0 auto; box-sizing: border-box;}",
    ".row { display: flex; gap: 20px; align-items: center; }",
    ".center { display: flex; align-items: center; justify-content: center; }",
    ".col { display: flex; flex-direction: column; gap: 20px; }",
    ".space-apart { display: flex; gap: 20px; justify-content: space-between; align-items: center; }",
    ":root {--accent-color: #13243F}",
    "button, .btn {all: unset; cursor: pointer; font-weight: bold; color: var(--accent-color); font-weight: 700; font-size: 1.3rem; text-transform: capitalize; padding: 15px 35px; border-radius: 3px; background-color: #fff; white-space: nowrap;}",
    "button.primary, .btn.primary { background-color: var(--accent-color); color: #fff; }",
    ".view-section { min-height: 100vh; color: var(--accent-color); overflow: hidden; scroll-snap-align: start;}",
    ".view-section h2 { font-size: 5rem; margin: 0; text-transform: uppercase; }",
    ".view-section p { font-size: 1.2rem; margin-bottom: 2rem; max-width: 800px; line-height: 1.5; }",
    "@media (max-width: 875px) { .view-section h2 { font-size: 4rem; margin-bottom: 5px; } .view-section p { font-size: 1.2rem; margin: 0 0 10px; } }",
    "@media (max-width: 425px) { .view-section h2 { font-size: 2.5rem; } .view-section p { font-size: 1rem; } }",
    ".thumbnail { position: relative; width: 100%; padding-top: 56.25%; overflow: hidden; background: #eee; border-radius: 3px; } ",
    ".thumbnail-1-1 { padding-top: 100%; }",
    ".thumbnail-9-16 { padding-top: 177.78%; } ",
    ".thumbnail > img { position: absolute; top: 0; left: 0; width: 100%; height: 100%; object-fit: cover; }",
    {
      "content": {
        ".return-btn": {
          "all": "unset",
          "cursor": "pointer",
          "opacity": 0,
          "animation": "close-btn-slide 0.5s 0.3s ease forwards"
        }
      }
    },
    {
      "content": {
        ".service-section": {
          "background": "#13243F",
          "color": "#FFFFFF",
          "position": "fixed",
          "top": 0,
          "left": 0,
          "zIndex": 1000,
          "width": "100vw",
          "height": "100vh",
          "animation": "bg-fade 0.5s ease forwards",
          "header": {
            "opacity": 0,
            "animation": "header-slide 0.7s ease forwards"
          },
          "h3": {
            "fontSize": "4rem",
            "margin": "10px 0 0",
            "textTransform": "capitalize"
          },
          "p": {
            "opacity": 0.8
          },
          "@media (max-width: 600px)": {
            "& h3": {
              "fontSize": "3rem"
            }
          },
          "@media (max-width: 425px)": {
            "& h3": {
              "fontSize": "2rem"
            }
          }
        }
      }
    },
    {
      "content": {
        "@keyframes bg-fade": {
          "from": {
            "background": "#5c87cd"
          },
          "to": {
            "background": "#13243F"
          }
        },
        "@keyframes header-slide": {
          "from": {
            "transform": "translateY(-50px)",
            "opacity": 0
          },
          "to": {
            "transform": "translateY(0)",
            "opacity": 1
          }
        },
        "@keyframes slide-up": {
          "from": {
            "transform": "translateY(50px)",
            "opacity": 0
          },
          "to": {
            "transform": "translateY(0)",
            "opacity": 1
          }
        },
        "@keyframes close-btn-slide": {
          "from": {
            "transform": "translateX(100px)",
            "opacity": 0
          },
          "to": {
            "transform": "translateX(0)",
            "opacity": 1
          }
        }
      }
    }
  ],
  "favicons": [
    {
      "rel": "icon",
      "type": "image/x-icon",
      "href": "favicon.ico"
    },
    {
      "rel": "apple-touch-icon",
      "sizes": "57x57",
      "href": "apple-icon-57x57.png"
    },
    {
      "rel": "apple-touch-icon",
      "sizes": "60x60",
      "href": "apple-icon-60x60.png"
    },
    {
      "rel": "apple-touch-icon",
      "sizes": "72x72",
      "href": "apple-icon-72x72.png"
    },
    {
      "rel": "apple-touch-icon",
      "sizes": "76x76",
      "href": "apple-icon-76x76.png"
    },
    {
      "rel": "apple-touch-icon",
      "sizes": "114x114",
      "href": "apple-icon-114x114.png"
    },
    {
      "rel": "apple-touch-icon",
      "sizes": "120x120",
      "href": "apple-icon-120x120.png"
    },
    {
      "rel": "apple-touch-icon",
      "sizes": "144x144",
      "href": "apple-icon-144x144.png"
    },
    {
      "rel": "apple-touch-icon",
      "sizes": "152x152",
      "href": "apple-icon-152x152.png"
    },
    {
      "rel": "apple-touch-icon",
      "sizes": "180x180",
      "href": "apple-icon-180x180.png"
    },
    {
      "rel": "icon",
      "type": "image/png",
      "sizes": "192x192",
      "href": "android-icon-192x192.png"
    },
    {
      "rel": "icon",
      "type": "image/png",
      "sizes": "32x32",
      "href": "favicon-32x32.png"
    },
    {
      "rel": "icon",
      "type": "image/png",
      "sizes": "96x96",
      "href": "favicon-96x96.png"
    },
    {
      "rel": "icon",
      "type": "image/png",
      "sizes": "16x16",
      "href": "favicon-16x16.png"
    }
  ],
  "links": [],
  "fonts": [
    "open-sans/OpenSans-Bold.ttf",
    "open-sans/OpenSans-ExtraBold.ttf",
    "open-sans/OpenSans-ExtraBoldItalic.ttf",
    "open-sans/OpenSans-BoldItalic.ttf",
    "open-sans/OpenSans-Regular.ttf",
    "open-sans/OpenSans-Italic.ttf",
    "open-sans/OpenSans-Light.ttf",
    "open-sans/OpenSans-LightItalic.ttf",
    "open-sans/OpenSans-Semibold.ttf",
    "open-sans/OpenSans-SemiboldItalic.ttf",
    "Fjalla_One/FjallaOne-Regular.ttf"
  ],
  "manifest": "manifest.json",
  "content": []
}
